neuroseries/__init__.py
neuroseries/interval_set.py
neuroseries/notebook_plots.py
neuroseries/time_series.py
neuroseries/tests/__init__.py
neuroseries/tests/test_neuroseries.py
neuroseries-0.3.3.dist-info/LICENSE.txt
neuroseries-0.3.3.dist-info/METADATA
neuroseries-0.3.3.dist-info/WHEEL
neuroseries-0.3.3.dist-info/top_level.txt
neuroseries-0.3.3.dist-info/RECORD
