Metadata-Version: 2.1
Name: neuroseries
Version: 0.3.3
Summary: neuro time series handling utilities
Home-page: https://github.com/MemDynLab/neuroseries
Author: Francesco P. Battaglia
Author-email: fpbattaglia@gmail.com
License: GPL3
Platform: UNKNOWN
Classifier: Development Status :: 3 - Alpha
Classifier: Intended Audience :: Science/Research
Classifier: License :: OSI Approved :: GNU General Public License v3 (GPLv3)
Classifier: Operating System :: OS Independent
Classifier: Programming Language :: Python :: 3 :: Only
Classifier: Topic :: Scientific/Engineering :: Bio-Informatics
Requires-Dist: numpy
Requires-Dist: pandas
Requires-Dist: scipy
Requires-Dist: parameterized
